{
  "main": {
    "id": "cd3ed1fb31455638",
    "type": "split",
    "children": [
      {
        "id": "2c0e2d6647f1c98e",
        "type": "tabs",
        "children": [
          {
            "id": "1c9ac2402b6fef2b",
            "type": "leaf",
            "state": {
              "type": "markdown",
              "state": {
                "file": "国网计算机.md",
                "mode": "source",
                "source": false
              },
              "icon": "lucide-file",
              "title": "国网计算机"
            }
          }
        ]
      }
    ],
    "direction": "vertical"
  },
  "left": {
    "id": "c7335643ffd46da0",
    "type": "split",
    "children": [
      {
        "id": "c61c6ef7a3388f89",
        "type": "tabs",
        "children": [
          {
            "id": "154bcf45a80e3ff1",
            "type": "leaf",
            "state": {
              "type": "file-explorer",
              "state": {
                "sortOrder": "alphabetical",
                "autoReveal": false
              },
              "icon": "lucide-folder-closed",
              "title": "文件列表"
            }
          },
          {
            "id": "89bf65657d8f442d",
            "type": "leaf",
            "state": {
              "type": "search",
              "state": {
                "query": "",
                "matchingCase": false,
                "explainSearch": false,
                "collapseAll": false,
                "extraContext": false,
                "sortOrder": "alphabetical"
              },
              "icon": "lucide-search",
              "title": "搜索"
            }
          },
          {
            "id": "eff16b81a758dc8b",
            "type": "leaf",
            "state": {
              "type": "bookmarks",
              "state": {},
              "icon": "lucide-bookmark",
              "title": "书签"
            }
          }
        ]
      }
    ],
    "direction": "horizontal",
    "width": 300
  },
  "right": {
    "id": "a9900df3beacdfe4",
    "type": "split",
    "children": [
      {
        "id": "179dde5b642372f4",
        "type": "tabs",
        "children": [
          {
            "id": "3df0a44860eb6656",
            "type": "leaf",
            "state": {
              "type": "backlink",
              "state": {
                "file": "Pasted image 20250918112059.png",
                "collapseAll": false,
                "extraContext": false,
                "sortOrder": "alphabetical",
                "showSearch": false,
                "searchQuery": "",
                "backlinkCollapsed": false,
                "unlinkedCollapsed": true
              },
              "icon": "links-coming-in",
              "title": "Pasted image 20250918112059 的反向链接列表"
            }
          },
          {
            "id": "81705568de87d97f",
            "type": "leaf",
            "state": {
              "type": "outgoing-link",
              "state": {
                "file": "Pasted image 20250918112059.png",
                "linksCollapsed": false,
                "unlinkedCollapsed": true
              },
              "icon": "links-going-out",
              "title": "Pasted image 20250918112059 的出链列表"
            }
          },
          {
            "id": "91e6c2e0496b18a5",
            "type": "leaf",
            "state": {
              "type": "tag",
              "state": {
                "sortOrder": "frequency",
                "useHierarchy": true,
                "showSearch": false,
                "searchQuery": ""
              },
              "icon": "lucide-tags",
              "title": "标签"
            }
          },
          {
            "id": "85056ba7cc369228",
            "type": "leaf",
            "state": {
              "type": "outline",
              "state": {
                "file": "Pasted image 20250918112059.png",
                "followCursor": false,
                "showSearch": false,
                "searchQuery": ""
              },
              "icon": "lucide-list",
              "title": "Pasted image 20250918112059 的大纲"
            }
          }
        ]
      }
    ],
    "direction": "horizontal",
    "width": 300,
    "collapsed": true
  },
  "left-ribbon": {
    "hiddenItems": {
      "switcher:打开快速切换": false,
      "graph:查看关系图谱": false,
      "canvas:新建白板": false,
      "daily-notes:打开/创建今天的日记": false,
      "templates:插入模板": false,
      "command-palette:打开命令面板": false,
      "bases:创建新数据库": false,
      "obsidian-git:Open Git source control": false
    }
  },
  "active": "1c9ac2402b6fef2b",
  "lastOpenFiles": [
    "zsh.md",
    "国网计算机.md",
    "nuitka.md",
    "git.md",
    "微服务.md",
    "wsl.md",
    "uv.md",
    "picgo.md",
    "Obsidian.md",
    "LLama-Factory.md",
    "docker.md",
    "cmd.md",
    "2025-9长城杯WP/easy_poison.md",
    "2025-9长城杯WP/大语言模型数据投毒.md",
    "assets/images/ce2e8757b99d8628738e772ce00decf3a76f94cbe7d62adc16d5041b737627d4523415d0159fa7cc3412dfd5ee2874daf0e4ff4e03eef2fff0f6ae43cea15f66.png",
    "assets/images/44497ae3d39aad2a354610c2d1fede9ef34820874f5e205802e24e985153e9bcf7f8fad100441792c96e84811d1096697b7e25e2b90b80b09fedf1187459c75c.png",
    "assets/images/4894d91806eaaa0838bcbe653b025a253a60a2c1888a77732a7afb572bf488d5d3967b9cc0012edb4fd76fa6de68157d8194229c131ed478533a9c840cda9fab.png",
    "assets/images/7eb2108b15dc498027b3b95f8af8d1fbf32904aa26c50a67044b6476ab4ee9503fde5593f976d787d69b664625627728c3d7f5dea5990866a964d7f588df1a08.png",
    "assets/images/29182b4d6ed26a2c14aaa4f81700e8d256c551fa5396a20976ba1f1c30d3a6dec1991e84a42d308bc427549ee38a0976a4249ee526ab6fa581fbdecfdd04f2ff.png",
    "2025-9长城杯WP",
    "assets/images/8e57c61518f003c8f7b58f753334fab99295ea429351e14c0ee13f154d8786515cc2c4c13acc7e123e0d388f8295eab671b823788bf302362d810ab2b48e63b3.png",
    "assets/images/f2f00ab09d918ffc5ae2dfee00cb584ca2ca1024677e65b7826e38c4c378698df7b0a9304a0c21cc960bcc597c03399e81d10b448d7dca011405e2b556fa2625.png",
    "assets/images/de14671499fc77c20cc0ad67510bc0faef428ece981b21d639a9cdaf35fd12cfd8d1246b3e6bb19191989121a649e28209fac9916280c7a730cd55a9f4d2844c.png",
    "assets/images/d3b3e58f72afd0400df7543a0b9618a10a17ee21611fccd7ea082dfb2f35013914d5fef6bd4ff151fb9abd9c69e97e122c5b447a9ea0ef7e3e1dcaa244406e26.png",
    "assets/images/d1a86d67b8a46db2237e91a71ef86286bd3e0f849a1071cf3fb93a87f51a9dd23dd92c4772c6c222471110289f05bb0b69fef3dd1d9f1bf24869a75239dc070d.png",
    "安装并配置kali-linux.md",
    "未命名.base",
    "assets/images",
    "assets",
    "Obsidian"
  ]
}